{"old": {"sanctions": 3405, "entities": 1844, "ar": 12, "au": 30, "ch": 199, "eu": 207, "gb": 214, "il": 7, "jp": 42, "ru": 7, "ua": 1257, "us": 1402, "Airplane": 1, "Company": 898, "LegalEntity": 172, "Organization": 782, "Person": 1552, "Vessel": 0}, "recent": {"sanctions": 1104, "entities": 685, "ar": 0, "au": 0, "ch": 361, "eu": 456, "gb": 26, "il": 0, "jp": 29, "ru": 0, "ua": 0, "us": 232, "Airplane": 0, "Company": 135, "LegalEntity": 5, "Organization": 60, "Person": 903, "Vessel": 1}, "all": {"sanctions": 4509, "entities": 2300, "ar": 12, "au": 30, "ch": 560, "eu": 663, "gb": 240, "il": 7, "jp": 71, "ru": 7, "ua": 1257, "us": 1634, "Airplane": 1, "Company": 1033, "LegalEntity": 177, "Organization": 842, "Person": 2455, "Vessel": 1}, "last_updated": "2022-03-04T08:07:46.502236"}