{"old": {"sanctions": 5937, "entities": 2863, "ar": 12, "au": 87, "be": 134, "ch": 193, "eu": 132, "gb": 219, "il": 12, "jp": 47, "kg": 210, "kz": 259, "nz": 0, "pl": 0, "ru": 7, "ua": 4327, "us": 254, "za": 16, "Company": 1667, "LegalEntity": 70, "Organization": 175, "Person": 4025}, "recent": {"sanctions": 26913, "entities": 9448, "ar": 1, "au": 1103, "be": 1380, "ch": 1758, "eu": 1380, "gb": 1326, "il": 0, "jp": 920, "kg": 3, "kz": 0, "nz": 1349, "pl": 22, "ru": 0, "ua": 16997, "us": 673, "za": 0, "Company": 8152, "LegalEntity": 204, "Organization": 2492, "Person": 16065}, "all": {"sanctions": 32850, "entities": 11800, "ar": 13, "au": 1190, "be": 1514, "ch": 1951, "eu": 1512, "gb": 1545, "il": 12, "jp": 967, "kg": 213, "kz": 259, "nz": 1349, "pl": 22, "ru": 7, "ua": 21324, "us": 927, "za": 16, "Company": 9819, "LegalEntity": 274, "Organization": 2667, "Person": 20090}, "last_updated": "2023-07-10T08:12:23.567784"}