{"old": {"sanctions": 3594, "entities": 1899, "ar": 12, "au": 145, "ch": 199, "eu": 180, "gb": 214, "il": 7, "jp": 42, "ru": 7, "ua": 1358, "us": 1402, "Airplane": 1, "Company": 907, "LegalEntity": 161, "Organization": 807, "Person": 1718, "Vessel": 0}, "recent": {"sanctions": 2753, "entities": 1031, "ar": 1, "au": 437, "ch": 565, "eu": 671, "gb": 732, "il": 0, "jp": 64, "ru": 0, "ua": 0, "us": 282, "Airplane": 0, "Company": 159, "LegalEntity": 51, "Organization": 114, "Person": 2428, "Vessel": 1}, "all": {"sanctions": 6347, "entities": 2525, "ar": 13, "au": 582, "ch": 764, "eu": 851, "gb": 946, "il": 7, "jp": 106, "ru": 7, "ua": 1358, "us": 1684, "Airplane": 1, "Company": 1066, "LegalEntity": 212, "Organization": 921, "Person": 4146, "Vessel": 1}, "last_updated": "2022-03-16T14:07:17.977801"}