{"old": {"sanctions": 4926, "entities": 3239, "ar": 12, "au": 155, "be": 177, "ch": 220, "eu": 177, "gb": 224, "il": 12, "jp": 48, "kg": 325, "nz": 0, "pl": 0, "ru": 11, "ua": 2102, "us": 1429, "za": 5, "Airplane": 1, "Company": 1277, "LegalEntity": 77, "Organization": 229, "Person": 3342, "Vessel": 0}, "recent": {"sanctions": 8891, "entities": 2471, "ar": 1, "au": 883, "be": 954, "ch": 1177, "eu": 954, "gb": 1147, "il": 0, "jp": 686, "kg": 0, "nz": 1111, "pl": 19, "ru": 0, "ua": 2, "us": 1956, "za": 0, "Airplane": 0, "Company": 1506, "LegalEntity": 126, "Organization": 259, "Person": 6997, "Vessel": 3}, "all": {"sanctions": 13817, "entities": 5089, "ar": 13, "au": 1038, "be": 1131, "ch": 1397, "eu": 1131, "gb": 1371, "il": 12, "jp": 734, "kg": 325, "nz": 1111, "pl": 19, "ru": 11, "ua": 2104, "us": 3385, "za": 5, "Airplane": 1, "Company": 2783, "LegalEntity": 203, "Organization": 488, "Person": 10339, "Vessel": 3}, "last_updated": "2022-12-10T08:09:21.035137"}